cronken/__init__.py
cronken/cronken.py
cronken/instance_heartbeat.lua
cronken/instance_reap.lua
cronken/json_models.py
cronken/run_finalize.lua
cronken/run_get_expired.lua
cronken/run_heartbeat.lua
cronken/run_init.lua
cronken-0.1.20.dist-info/LICENSE
cronken-0.1.20.dist-info/METADATA
cronken-0.1.20.dist-info/WHEEL
cronken-0.1.20.dist-info/RECORD
