Metadata-Version: 2.1
Name: cronken
Version: 0.1.20
Summary: 
Home-page: https://github.com/populi/cronken
Author: Clint Olson
Author-email: clint@populi.co
Requires-Python: >=3.8,<4.0
Classifier: Programming Language :: Python :: 3
Classifier: Programming Language :: Python :: 3.8
Classifier: Programming Language :: Python :: 3.9
Classifier: Programming Language :: Python :: 3.10
Classifier: Programming Language :: Python :: 3.11
Classifier: Programming Language :: Python :: 3.12
Requires-Dist: apscheduler (<4.0.0)
Requires-Dist: coredis (>=4.17.0,<5.0.0)
Requires-Dist: pydantic (>=2.4.2,<3.0.0)
Project-URL: Repository, https://github.com/populi/cronken
